mehdashti_pagination/__init__.py
mehdashti_pagination/core.py
mehdashti_pagination/py.typed
mehdashti_pagination-0.1.0.dist-info/METADATA
mehdashti_pagination-0.1.0.dist-info/WHEEL
mehdashti_pagination-0.1.0.dist-info/RECORD
